jokes/__init__.py
jokes/jokes.py
python_template_zuppif-0.1.3.dist-info/METADATA
python_template_zuppif-0.1.3.dist-info/WHEEL
python_template_zuppif-0.1.3.dist-info/entry_points.txt
python_template_zuppif-0.1.3.dist-info/licenses/LICENSE
python_template_zuppif-0.1.3.dist-info/RECORD
