Metadata-Version: 2.4
Name: python-template-zuppif
Version: 0.1.3
Summary: Add your description here
License-File: LICENSE
Requires-Python: >=3.12
Requires-Dist: requests>=2.32.3
